testrepo994/__init__.py
testrepo994/py.typed
TestRepo994-0.0.0.dist-info/LICENSE
TestRepo994-0.0.0.dist-info/METADATA
TestRepo994-0.0.0.dist-info/WHEEL
TestRepo994-0.0.0.dist-info/top_level.txt
TestRepo994-0.0.0.dist-info/RECORD
