Metadata-Version: 2.1
Name: TestRepo994
Version: 0.0.0
Summary: Replace This Text With Your Project's
Author: Armin Ariamajd
Maintainer: Armin Ariamajd
License: GNU AFFERO GENERAL PUBLIC LICENSE
Project-URL: Documentation, https://aariam.github.io/TestRepo994
Project-URL: Download, https://github.com/AAriam/TestRepo994/releases
Project-URL: Homepage, https://aariam.github.io/TestRepo994
Project-URL: Issue-Tracker, https://github.com/AAriam/TestRepo994/issues
Project-URL: News, https://aariam.github.io/TestRepo994/news
Project-URL: Source, https://github.com/AAriam/TestRepo994
Project-URL: Sponsor, https://aariam.github.io/TestRepo994/contribute/collaborate/maintain/sponsor
Keywords: First Keyword,Second Keyword,Third Keyword
Classifier: License :: OSI Approved :: GNU Affero General Public License v3 or later (AGPLv3+)
Classifier: Natural Language :: English
Classifier: Operating System :: POSIX :: Linux
Classifier: Programming Language :: Python :: 3 :: Only
Classifier: Programming Language :: Python :: 3.12
Classifier: Typing :: Typed
Requires-Python: >=3.12
License-File: LICENSE
